{"saes":[{"id":"COOP-021","titre":"La chenille géante — On avance ensemble","niveau":"Préscolaire","cycle":"Préscolaire","duree_periodes":1,"competence_pfeq":"Agir dans divers contextes de pratique d'activités physiques","composante":"Exécuter des mouvements locomoteurs en coopération","moyen_action":"Jeux coopératifs locomoteurs","tags":["coopération","locomotion","préscolaire","chenille","synchronisation"],"_idx":0},{"id":"COOP-022","titre":"Le radeau de sauvetage — Personne ne reste à l'eau","niveau":"Primaire","cycle":"Cycle 1 Primaire","duree_periodes":2,"competence_pfeq":"Agir dans divers contextes de pratique d'activités physiques","composante":"Mobiliser ses ressources dans la coopération","moyen_action":"Jeux coopératifs d'équilibre et résolution de problèmes","tags":["coopération","équilibre","résolution de problèmes","cycle1","primaire"],"_idx":1},{"id":"COOP-023","titre":"Le pont humain — Traverser la rivière ensemble","niveau":"Primaire","cycle":"Cycle 2 Primaire","duree_periodes":2,"competence_pfeq":"Interagir dans divers contextes de pratique d'activités physiques","composante":"Coopérer à l'élaboration et à l'application d'un plan d'action","moyen_action":"Jeux coopératifs de portée et stabilité","tags":["coopération","construction","force","stabilité","cycle2","primaire"],"_idx":2},{"id":"COOP-024","titre":"L'orchestre corporel — Le rythme du groupe","niveau":"Préscolaire","cycle":"Préscolaire","duree_periodes":1,"competence_pfeq":"Agir dans divers contextes de pratique d'activités physiques","composante":"Exécuter des actions motrices en synchronisation avec les pairs","moyen_action":"Expression corporelle et percussions","tags":["coopération","rythme","expression corporelle","préscolaire","musique"],"_idx":3},{"id":"COOP-025","titre":"Le déménagement coopératif — Transporter sans échapper","niveau":"Primaire","cycle":"Cycle 1 Primaire","duree_periodes":2,"competence_pfeq":"Interagir dans divers contextes de pratique d'activités physiques","composante":"Élaborer un plan d'action coopératif","moyen_action":"Jeux coopératifs de transport et manipulation","tags":["coopération","transport","manipulation","cycle1","primaire"],"_idx":4},{"id":"COOP-026","titre":"Le labyrinthe vivant — Guides et explorateurs","niveau":"Primaire","cycle":"Cycle 2 Primaire","duree_periodes":2,"competence_pfeq":"Interagir dans divers contextes de pratique d'activités physiques","composante":"Communiquer avec ses partenaires dans un contexte de coopération","moyen_action":"Jeux coopératifs d'orientation et communication","tags":["coopération","orientation","communication","confiance","cycle2","primaire"],"_idx":5},{"id":"COOP-027","titre":"La machine humaine — Engrenages synchronisés","niveau":"Primaire","cycle":"Cycle 3 Primaire","duree_periodes":2,"competence_pfeq":"Interagir dans divers contextes de pratique d'activités physiques","composante":"Élaborer et appliquer un plan d'action collectif","moyen_action":"Expression corporelle coopérative","tags":["coopération","expression corporelle","créativité","cycle3","primaire","machine"],"_idx":6},{"id":"COOP-028","titre":"Le parachute arc-en-ciel — Défis collectifs","niveau":"Préscolaire","cycle":"Préscolaire","duree_periodes":1,"competence_pfeq":"Agir dans divers contextes de pratique d'activités physiques","composante":"Exécuter des actions motrices coordonnées avec le groupe","moyen_action":"Jeux coopératifs avec parachute","tags":["coopération","parachute","préscolaire","motricité globale","groupe"],"_idx":7},{"id":"COOP-029","titre":"La toile d'araignée coopérative — Tisser des liens","niveau":"Primaire","cycle":"Cycle 2 Primaire","duree_periodes":2,"competence_pfeq":"Interagir dans divers contextes de pratique d'activités physiques","composante":"Élaborer un plan d'action et coopérer à son application","moyen_action":"Jeux coopératifs de résolution de problèmes moteurs","tags":["coopération","résolution de problèmes","souplesse","cycle2","primaire","toile"],"_idx":8},{"id":"COOP-030","titre":"Le dragon coopératif — Protéger la queue","niveau":"Primaire","cycle":"Cycle 3 Primaire","duree_periodes":2,"competence_pfeq":"Interagir dans divers contextes de pratique d'activités physiques","composante":"Coopérer à l'atteinte d'un objectif commun de groupe","moyen_action":"Jeux coopératifs de poursuite et protection","tags":["coopération","poursuite","protection","dragon","cycle3","primaire","Chine"],"_idx":9},{"id":"COOP-031","titre":"Le relais stratégique — Course à décisions partagées","niveau":"Secondaire","cycle":"Secondaire 1","duree_periodes":2,"competence_pfeq":"Interagir dans divers contextes de pratique d'activités physiques","composante":"Élaborer un plan d'action collectif et l'ajuster en cours de route","moyen_action":"Jeux coopératifs de course et stratégie","tags":["coopération","relais","stratégie","secondaire1","course"],"_idx":10},{"id":"COOP-032","titre":"Le défi survie — Construire un abri en équipe","niveau":"Secondaire","cycle":"Secondaire 1","duree_periodes":2,"competence_pfeq":"Interagir dans divers contextes de pratique d'activités physiques","composante":"Élaborer et appliquer un plan d'action en coopération","moyen_action":"Jeux coopératifs de construction et plein air","tags":["coopération","construction","survie","secondaire1","résolution de problèmes"],"_idx":11},{"id":"COOP-033","titre":"Le code secret — Communication tactique en mouvement","niveau":"Secondaire","cycle":"Secondaire 2","duree_periodes":2,"competence_pfeq":"Interagir dans divers contextes de pratique d'activités physiques","composante":"Communiquer de façon stratégique avec ses partenaires","moyen_action":"Jeux coopératifs de stratégie et communication","tags":["coopération","stratégie","communication","handball","secondaire2","codes"],"_idx":12},{"id":"COOP-034","titre":"Le parcours impossible — Résolution collective de défis moteurs","niveau":"Secondaire","cycle":"Secondaire 2","duree_periodes":2,"competence_pfeq":"Interagir dans divers contextes de pratique d'activités physiques","composante":"Coopérer à la résolution d'un problème moteur complexe","moyen_action":"Parcours coopératifs de résolution de problèmes","tags":["coopération","résolution de problèmes","secondaire2","parcours","défis"],"_idx":13},{"id":"COOP-035","titre":"L'expédition polaire — Survivre ensemble au froid","niveau":"Secondaire","cycle":"Secondaire 3","duree_periodes":3,"competence_pfeq":"Interagir dans divers contextes de pratique d'activités physiques","composante":"Exercer un leadership coopératif et assumer des responsabilités partagées","moyen_action":"Simulation coopérative d'expédition et conditionnement physique","tags":["coopération","expédition","survie","secondaire3","leadership","conditionnement"],"_idx":14},{"id":"COOP-036","titre":"Le tournoi coopératif inversé — Gagner en aidant","niveau":"Secondaire","cycle":"Secondaire 3","duree_periodes":2,"competence_pfeq":"Interagir dans divers contextes de pratique d'activités physiques","composante":"Manifester un comportement éthique et coopératif en contexte sportif","moyen_action":"Sports collectifs en format coopératif","tags":["coopération","volleyball","esprit sportif","secondaire3","tournoi","entraide"],"_idx":15},{"id":"COOP-037","titre":"Le sauvetage en mer — Mission aquatique coopérative","niveau":"Secondaire","cycle":"Secondaire 4","duree_periodes":2,"competence_pfeq":"Interagir dans divers contextes de pratique d'activités physiques","composante":"Coopérer dans un contexte aquatique sécuritaire","moyen_action":"Activités aquatiques coopératives","tags":["coopération","natation","sauvetage","secondaire4","piscine","sécurité"],"_idx":16},{"id":"COOP-038","titre":"Le marathon coopératif — Chaque foulée compte","niveau":"Secondaire","cycle":"Secondaire 4","duree_periodes":3,"competence_pfeq":"Adopter un mode de vie sain et actif","composante":"S'engager dans une pratique régulière d'activités physiques avec ses pairs","moyen_action":"Course d'endurance coopérative","tags":["coopération","endurance","course","secondaire4","marathon","cardiovasculaire"],"_idx":17},{"id":"COOP-039","titre":"Le projet sportif communautaire — Concevoir pour les autres","niveau":"Secondaire","cycle":"Secondaire 5","duree_periodes":4,"competence_pfeq":"Interagir dans divers contextes de pratique d'activités physiques","composante":"Assumer des rôles de leader et d'organisateur dans un projet sportif coopératif","moyen_action":"Projet coopératif d'animation sportive communautaire","tags":["coopération","leadership","communautaire","secondaire5","animation","projet"],"_idx":18},{"id":"COOP-040","titre":"L'olympiade coopérative — Médailles d'entraide","niveau":"Secondaire","cycle":"Secondaire 5","duree_periodes":3,"competence_pfeq":"Interagir dans divers contextes de pratique d'activités physiques","composante":"Démontrer un comportement éthique, coopératif et inclusif dans un contexte compétitif","moyen_action":"Olympiade multi-sports coopérative","tags":["coopération","olympiade","multi-sports","secondaire5","fin d'année","célébration"],"_idx":19},{"id":"COOP-041","titre":"Les bâtisseurs de tour — Empiler sans parler","niveau":"Préscolaire","cycle":"Préscolaire","duree_periodes":1,"competence_pfeq":"Agir dans divers contextes de pratique d'activités physiques","composante":"Exécuter des actions de manipulation en coopération","moyen_action":"Jeux coopératifs de construction et motricité fine","tags":["coopération","construction","silence","préscolaire","motricité fine"],"_idx":20},{"id":"COOP-042","titre":"Le tapis volant — Transport magique collectif","niveau":"Primaire","cycle":"Cycle 1 Primaire","duree_periodes":2,"competence_pfeq":"Agir dans divers contextes de pratique d'activités physiques","composante":"Mobiliser ses ressources motrices dans un contexte coopératif","moyen_action":"Jeux coopératifs de force et coordination","tags":["coopération","force","transport","cycle1","primaire","tapis"],"_idx":21},{"id":"COOP-043","titre":"Le GPS humain — Navigation coopérative au gymnase","niveau":"Primaire","cycle":"Cycle 3 Primaire","duree_periodes":2,"competence_pfeq":"Interagir dans divers contextes de pratique d'activités physiques","composante":"Communiquer pour coopérer à l'atteinte d'un objectif commun","moyen_action":"Jeux coopératifs d'orientation et de communication","tags":["coopération","orientation","GPS","communication","cycle3","primaire"],"_idx":22},{"id":"COOP-044","titre":"Le cirque coopératif — Acrobaties à plusieurs","niveau":"Primaire","cycle":"Cycle 3 Primaire","duree_periodes":3,"competence_pfeq":"Interagir dans divers contextes de pratique d'activités physiques","composante":"Coopérer à la création et à la présentation d'une séquence motrice","moyen_action":"Arts du cirque coopératifs","tags":["coopération","cirque","acrobatie","cycle3","primaire","spectacle"],"_idx":23},{"id":"COOP-045","titre":"Le soccer coopératif — 5 passes avant de marquer","niveau":"Secondaire","cycle":"Secondaire 1","duree_periodes":2,"competence_pfeq":"Interagir dans divers contextes de pratique d'activités physiques","composante":"Coopérer dans un sport collectif en favorisant l'inclusion","moyen_action":"Sports collectifs modifiés pour la coopération","tags":["coopération","soccer","inclusion","secondaire1","sport collectif","passes"],"_idx":24},{"id":"COOP-046","titre":"Le défi Ninja coopératif — Arts martiaux en synchronisation","niveau":"Secondaire","cycle":"Secondaire 2","duree_periodes":2,"competence_pfeq":"Interagir dans divers contextes de pratique d'activités physiques","composante":"Coopérer à la création d'une séquence motrice synchronisée","moyen_action":"Arts martiaux coopératifs et expression corporelle","tags":["coopération","arts martiaux","kata","secondaire2","synchronisation","création"],"_idx":25},{"id":"COOP-047","titre":"Le triathlon d'équipe — Forces complémentaires","niveau":"Secondaire","cycle":"Secondaire 3","duree_periodes":2,"competence_pfeq":"Adopter un mode de vie sain et actif","composante":"S'engager dans un effort physique soutenu avec le soutien de ses pairs","moyen_action":"Multi-sports coopératifs d'endurance","tags":["coopération","triathlon","endurance","secondaire3","multi-sports","complémentarité"],"_idx":26},{"id":"COOP-048","titre":"Le laboratoire de mouvement — Recherche coopérative en biomécanique","niveau":"Secondaire","cycle":"Secondaire 4","duree_periodes":3,"competence_pfeq":"Interagir dans divers contextes de pratique d'activités physiques","composante":"Coopérer dans un processus d'analyse et d'amélioration de la performance","moyen_action":"Analyse biomécanique coopérative","tags":["coopération","biomécanique","analyse","secondaire4","recherche","coaching"],"_idx":27},{"id":"COOP-049","titre":"L'escape room sportif — Résoudre pour s'évader","niveau":"Secondaire","cycle":"Secondaire 4","duree_periodes":2,"competence_pfeq":"Interagir dans divers contextes de pratique d'activités physiques","composante":"Coopérer sous pression pour résoudre des problèmes complexes","moyen_action":"Jeux coopératifs d'évasion et résolution de problèmes","tags":["coopération","escape room","énigmes","secondaire4","résolution de problèmes","chrono"],"_idx":28},{"id":"COOP-050","titre":"Le défi des générations — Enseigner et apprendre à travers les âges","niveau":"Secondaire","cycle":"Secondaire 5","duree_periodes":3,"competence_pfeq":"Interagir dans divers contextes de pratique d'activités physiques","composante":"Assumer un rôle de mentor sportif et coopérer avec des partenaires d'âges variés","moyen_action":"Mentorat sportif intergénérationnel","tags":["coopération","mentorat","intergénérationnel","secondaire5","enseignement","transmission"],"_idx":29},{"id":"COOP-051","titre":"Le train coopératif — Locomotion en file avec défis","niveau":"Préscolaire","cycle":"Préscolaire","duree_periodes":1,"competence_pfeq":"Agir dans divers contextes de pratique d'activités physiques","composante":"Exécuter des mouvements locomoteurs en coopération","moyen_action":"Jeux coopératifs locomoteurs","tags":["coopération","locomotion","préscolaire","train","parcours","déplacement en file"],"_idx":30},{"id":"COOP-052","titre":"Les sculpteurs vivants — Créer des formes humaines en équipe","niveau":"Primaire","cycle":"Cycle 1 Primaire","duree_periodes":2,"competence_pfeq":"Agir dans divers contextes de pratique d'activités physiques","composante":"Mobiliser ses ressources pour créer des formes corporelles en coopération","moyen_action":"Jeux coopératifs de créativité corporelle","tags":["coopération","créativité corporelle","cycle1","primaire","sculptures","formes","équilibre statique"],"_idx":31},{"id":"COOP-053","titre":"Le ballon voyageur — Transport sans les mains en relais","niveau":"Primaire","cycle":"Cycle 2 Primaire","duree_periodes":2,"competence_pfeq":"Agir dans divers contextes de pratique d'activités physiques","composante":"Exécuter des actions de manipulation coopératives","moyen_action":"Jeux coopératifs de manipulation et relais","tags":["coopération","manipulation","relais","cycle2","primaire","ballon","transport","coordination"],"_idx":32},{"id":"COOP-054","titre":"La carte au trésor — Course d'orientation coopérative","niveau":"Primaire","cycle":"Cycle 3 Primaire","duree_periodes":3,"competence_pfeq":"Interagir dans divers contextes de pratique d'activités physiques","composante":"Coopérer à l'élaboration et à l'application d'un plan d'action collectif","moyen_action":"Course d'orientation coopérative et résolution de problèmes","tags":["coopération","course d'orientation","cycle3","primaire","carte","boussole","plein air","résolution de problèmes"],"_idx":33},{"id":"COOP-055","titre":"Le volleyball inversé — Aider l'adversaire à réussir","niveau":"Secondaire 1","cycle":"Secondaire 1","duree_periodes":3,"competence_pfeq":"Interagir dans divers contextes de pratique d'activités physiques","composante":"Élaborer un plan d'action coopératif et adapter ses actions pour soutenir l'adversaire","moyen_action":"Sports collectifs revisités — volleyball coopératif","tags":["coopération","volleyball","secondaire1","sport inversé","bienveillance","techniques volleyball","pensée critique"],"_idx":34},{"id":"COOP-056","titre":"Le défi fitness collectif — AMRAP en équipe","niveau":"Secondaire 2","cycle":"Secondaire 2","duree_periodes":2,"competence_pfeq":"Adopter un mode de vie sain et actif","composante":"Planifier et mettre en œuvre un programme d'entraînement coopératif adapté","moyen_action":"Entraînement fonctionnel coopératif (AMRAP)","tags":["coopération","AMRAP","fitness","secondaire2","entraînement fonctionnel","endurance","encouragement"],"_idx":35},{"id":"COOP-057","titre":"La chorégraphie sportive — Danse et sport fusionnés","niveau":"Secondaire 3","cycle":"Secondaire 3","duree_periodes":4,"competence_pfeq":"Interagir dans divers contextes de pratique d'activités physiques","composante":"Créer et présenter une chorégraphie sportive collective intégrant danse et habiletés motrices","moyen_action":"Danse créative et habiletés sportives fusionnées","tags":["coopération","chorégraphie","danse","sport","secondaire3","création","performance","synchronisation"],"_idx":36},{"id":"COOP-058","titre":"Le Spikeball coopératif — Tournoi à rotation inclusive","niveau":"Secondaire 3","cycle":"Secondaire 3","duree_periodes":3,"competence_pfeq":"Interagir dans divers contextes de pratique d'activités physiques","composante":"Adapter ses actions motrices en fonction du partenaire et du contexte coopératif","moyen_action":"Sport émergent — Spikeball coopératif et tournoi inclusif","tags":["coopération","spikeball","secondaire3","tournoi inclusif","sport émergent","rotation","adaptabilité"],"_idx":37},{"id":"COOP-059","titre":"Le projet bien-être — Concevoir un programme d'entraînement pour un pair","niveau":"Secondaire 4","cycle":"Secondaire 4","duree_periodes":5,"competence_pfeq":"Adopter un mode de vie sain et actif","composante":"Planifier une démarche visant à modifier certaines habitudes de vie en matière de santé","moyen_action":"Planification d'entraînement personnalisé et mentorat entre pairs","tags":["coopération","entraînement","planification","secondaire4","mentorat","bien-être","programme personnalisé","empathie"],"_idx":38},{"id":"COOP-060","titre":"Le débat sportif actif — Argumenter en bougeant","niveau":"Secondaire 5","cycle":"Secondaire 5","duree_periodes":3,"competence_pfeq":"Adopter un mode de vie sain et actif","composante":"Analyser les enjeux liés à la pratique d'activités physiques et formuler des arguments éclairés","moyen_action":"Débat actif et activité physique combinés","tags":["coopération","débat","pensée critique","secondaire5","argumentation","activité physique","enjeux sociaux","réflexion"],"_idx":39}]}